spectral_synthesizer/Base_Models/Flux_Model.py
spectral_synthesizer/Base_Models/RV_generator.py
spectral_synthesizer/Base_Models/SimulationObject.py
spectral_synthesizer/Base_Models/Time_representation.py
spectral_synthesizer/Base_Models/__init__.py
spectral_synthesizer/RV_generation/ConstRV.py
spectral_synthesizer/RV_generation/Keplerians.py
spectral_synthesizer/RV_generation/RandomRV.py
spectral_synthesizer/RV_generation/__init__.py
spectral_synthesizer/Sampling_Times/CustomWindow.py
spectral_synthesizer/Sampling_Times/TimeWindow.py
spectral_synthesizer/Sampling_Times/__init__.py
spectral_synthesizer/SpectralSimulator.py
spectral_synthesizer/__init__.py
spectral_synthesizer/data_interfaces/SimulatedSpectra.py
spectral_synthesizer/data_interfaces/SpectraHolder.py
spectral_synthesizer/data_interfaces/__init__.py
spectral_synthesizer/outside_tools/generate_from_yaml.py
spectral_synthesizer/spectra_generation/ManagerProxy.py
spectral_synthesizer/spectra_generation/OBSERVATION_MODEL.py
spectral_synthesizer/spectra_generation/PHOENIX_MODEL.py
spectral_synthesizer/spectra_generation/__init__.py
spectral_synthesizer/spectral_effects/RandomNoise.py
spectral_synthesizer/spectral_effects/__init__.py
spectral_synthesizer/spectral_effects/stellar_activity/__init__.py
spectral_synthesizer/spectral_effects/telluric_features/__init__.py
spectral_synthesizer/utils/__init__.py
spectral_synthesizer/utils/data_types.py
spectral_synthesizer/utils/keplerian.py
spectral_synthesizer/utils/shift_spectra.py
spectral_synthesizer/utils/units.py
spectral_synthesizer/utils/work_packages.py
spectral_synthesizer-0.1.3.dist-info/WHEEL
spectral_synthesizer-0.1.3.dist-info/METADATA
spectral_synthesizer-0.1.3.dist-info/RECORD
