Metadata-Version: 2.1
Name: spectral-synthesizer
Version: 0.1.3
Summary: Generate synthetic spectra with injected RVs
Author: Kamuish
Author-email: andremiguel952@gmail.com
Requires-Python: >=3.8,<4.0
Classifier: Programming Language :: Python :: 3
Classifier: Programming Language :: Python :: 3.10
Classifier: Programming Language :: Python :: 3.8
Classifier: Programming Language :: Python :: 3.9
Requires-Dist: numpy (>=1.22.3,<2.0.0)
Requires-Dist: tabletexifier (>=0.1.9,<0.2.0)
